fugent_model/__init__.py
fugent_model/__main__.py
fugent_model/environment.py
fugent_model/model.py
fugent_model/requirements.txt
fugent_model/run.py
fugent_model/train.py
fugent_model-0.0.4.dist-info/METADATA
fugent_model-0.0.4.dist-info/WHEEL
fugent_model-0.0.4.dist-info/licenses/LICENSE
fugent_model-0.0.4.dist-info/RECORD
